; Test.j

; Generated by ClassFileAnalyzer (Can)
; Analyzer and Disassembler for Java class files
; (Jasmin syntax 2, http://jasmin.sourceforge.net)
;
; ClassFileAnalyzer, version 0.7.0 


.bytecode 52.0
.source Test.java
.class public Test
.super java/lang/Object
.inner class somthing inner Test$1somthing ; <not a member>

.method public <init>()V
  .limit stack 1
  .limit locals 1
  .line 2
  0: aload_0
  1: invokespecial java/lang/Object/<init>()V
  4: return
.end method

.method public static main([Ljava/lang/String;)V
  .limit stack 3
  .limit locals 2
  .line 13
  0: ldc "salam"
  2: astore_1
  .line 14
  3: new Test$1somthing
  6: dup
  7: aload_1
  8: invokespecial Test$1somthing/<init>(Ljava/lang/String;)V
  11: pop
  .line 16
  12: return
.end method


